diffdoc/__init__.py
diffdoc/cli.py
diffdoc/compiler.py
diffdoc/diff.py
diffdoc/parser.py
diffdoc/rst.py
diff_doc-0.1.0.dist-info/METADATA
diff_doc-0.1.0.dist-info/WHEEL
diff_doc-0.1.0.dist-info/entry_points.txt
diff_doc-0.1.0.dist-info/top_level.txt
diff_doc-0.1.0.dist-info/RECORD
