Metadata-Version: 2.1
Name: diff-doc
Version: 0.1.0
Summary: UNKNOWN
Home-page: http://github.com/mwilliamson/diff-doc
Author: Michael Williamson
Author-email: mike@zwobble.org
License: UNKNOWN
Keywords: diff doc example tutorial
Platform: UNKNOWN
Classifier: Development Status :: 4 - Beta
Classifier: Intended Audience :: Developers
Classifier: Programming Language :: Python
Classifier: Programming Language :: Python :: 3
Classifier: Programming Language :: Python :: 3.5
Classifier: Programming Language :: Python :: 3.6
